ovos_stt_plugin_fasterwhisper_zuazo/__init__.py
ovos_stt_plugin_fasterwhisper_zuazo/version.py
ovos_stt_plugin_fasterwhisper_zuazo-0.1.4.dist-info/LICENSE
ovos_stt_plugin_fasterwhisper_zuazo-0.1.4.dist-info/METADATA
ovos_stt_plugin_fasterwhisper_zuazo-0.1.4.dist-info/WHEEL
ovos_stt_plugin_fasterwhisper_zuazo-0.1.4.dist-info/entry_points.txt
ovos_stt_plugin_fasterwhisper_zuazo-0.1.4.dist-info/top_level.txt
ovos_stt_plugin_fasterwhisper_zuazo-0.1.4.dist-info/zip-safe
ovos_stt_plugin_fasterwhisper_zuazo-0.1.4.dist-info/RECORD
