Metadata-Version: 2.1
Name: ovos-stt-plugin-fasterwhisper-zuazo
Version: 0.1.4
Summary: A pt / gl / es / ca / eu  - fasterwhisper stt plugin for OVOS
Home-page: https://github.com/OpenVoiceOS/ovos-stt-plugin-fasterwhisper-zuazo
Author: JarbasAi
Author-email: jarbasai@mailfence.com
License: Apache-2.0
Keywords: mycroft ovos plugin stt
Classifier: Development Status :: 3 - Alpha
Classifier: Intended Audience :: Developers
Classifier: Topic :: Text Processing :: Linguistic
Classifier: License :: OSI Approved :: Apache Software License
Classifier: Programming Language :: Python :: 2
Classifier: Programming Language :: Python :: 2.7
Classifier: Programming Language :: Python :: 3
Classifier: Programming Language :: Python :: 3.0
Classifier: Programming Language :: Python :: 3.1
Classifier: Programming Language :: Python :: 3.2
Classifier: Programming Language :: Python :: 3.3
Classifier: Programming Language :: Python :: 3.4
Classifier: Programming Language :: Python :: 3.5
Classifier: Programming Language :: Python :: 3.6
License-File: LICENSE
Requires-Dist: ovos-plugin-manager<2.0.0,>=1.0.0
Requires-Dist: SpeechRecognition>=3.8.1
Requires-Dist: ovos-stt-plugin-fasterwhisper<1.0.0,>=0.0.1
Requires-Dist: requests
